pytest_playwright/__init__.py
pytest_playwright/pytest_playwright.py
liuxiankun_pytest_playwright1-0.0.4.dist-info/METADATA
liuxiankun_pytest_playwright1-0.0.4.dist-info/WHEEL
liuxiankun_pytest_playwright1-0.0.4.dist-info/entry_points.txt
liuxiankun_pytest_playwright1-0.0.4.dist-info/top_level.txt
liuxiankun_pytest_playwright1-0.0.4.dist-info/RECORD
