Metadata-Version: 2.1
Name: liuxiankun-pytest-playwright1
Version: 0.0.4
Summary: A small example package
Home-page: UNKNOWN
Author: liuxiankun
Author-email: 939449414@qq.com
License: UNKNOWN
Platform: UNKNOWN
Classifier: Programming Language :: Python :: 3
Classifier: Programming Language :: Python :: 3.7
Classifier: Programming Language :: Python :: 3.8
Classifier: Programming Language :: Python :: 3.9
Classifier: Programming Language :: Python :: 3.10
Classifier: License :: OSI Approved :: Apache Software License
Classifier: Operating System :: OS Independent
Classifier: Framework :: Pytest
Requires-Dist: playwright (>=1.13)
Requires-Dist: pytest
Requires-Dist: pytest-base-url
Requires-Dist: python-slugify
